{"result": {"first_blood_time": 129, "dire_name": "Gigabyte.Mineski", "tower_status_dire": 36, "barracks_status_radiant": 63, "start_time": 1400396855, "players": [{"tower_damage": 200, "item_5": 0, "deaths": 4, "kills": 6, "last_hits": 18, "account_id": 45614257, "ability_upgrades": [{"level": 1, "ability": 5435, "time": 870}, {"level": 2, "ability": 5436, "time": 959}, {"level": 3, "ability": 5436, "time": 1074}, {"level": 4, "ability": 5435, "time": 1218}, {"level": 5, "ability": 5436, "time": 1382}, {"level": 6, "ability": 5437, "time": 1565}, {"level": 7, "ability": 5436, "time": 1661}, {"level": 8, "ability": 5434, "time": 1930}, {"level": 9, "ability": 5435, "time": 2151}, {"level": 10, "ability": 5435, "time": 2379}, {"level": 11, "ability": 5437, "time": 2874}, {"level": 12, "ability": 5434, "time": 3761}, {"level": 13, "ability": 5434, "time": 3764}], "assists": 4, "hero_damage": 2807, "denies": 2, "gold": 3406, "hero_healing": 1352, "level": 13, "leaver_status": 0, "gold_spent": 8595, "item_1": 1, "item_0": 29, "item_2": 46, "player_slot": 0, "gold_per_min": 239, "item_3": 92, "xp_per_min": 207, "hero_id": 83, "item_4": 46}, {"tower_damage": 1831, "item_5": 30, "deaths": 4, "kills": 2, "last_hits": 56, "account_id": 101460882, "ability_upgrades": [{"level": 1, "ability": 5299, "time": 866}, {"level": 2, "ability": 5297, "time": 920}, {"level": 3, "ability": 5299, "time": 999}, {"level": 4, "ability": 5298, "time": 1147}, {"level": 5, "ability": 5299, "time": 1268}, {"level": 6, "ability": 5298, "time": 1358}, {"level": 7, "ability": 5299, "time": 1525}, {"level": 8, "ability": 5298, "time": 1571}, {"level": 9, "ability": 5300, "time": 1825}, {"level": 10, "ability": 5298, "time": 1923}, {"level": 11, "ability": 5300, "time": 2162}, {"level": 12, "ability": 5297, "time": 2580}, {"level": 13, "ability": 5297, "time": 2909}, {"level": 14, "ability": 5297, "time": 3285}, {"level": 15, "ability": 5002, "time": 3710}], "assists": 13, "hero_damage": 7691, "denies": 4, "gold": 3071, "hero_healing": 0, "level": 15, "leaver_status": 0, "gold_spent": 10400, "item_1": 190, "item_0": 34, "item_2": 180, "player_slot": 1, "gold_per_min": 275, "item_3": 46, "xp_per_min": 264, "hero_id": 64, "item_4": 108}, {"tower_damage": 1329, "item_5": 21, "deaths": 6, "kills": 8, "last_hits": 177, "account_id": 91191651, "ability_upgrades": [{"level": 1, "ability": 5218, "time": 868}, {"level": 2, "ability": 5220, "time": 899}, {"level": 3, "ability": 5219, "time": 937}, {"level": 4, "ability": 5219, "time": 1006}, {"level": 5, "ability": 5220, "time": 1071}, {"level": 6, "ability": 5221, "time": 1171}, {"level": 7, "ability": 5219, "time": 1317}, {"level": 8, "ability": 5219, "time": 1382}, {"level": 9, "ability": 5220, "time": 1556}, {"level": 10, "ability": 5220, "time": 1749}, {"level": 11, "ability": 5221, "time": 1800}, {"level": 12, "ability": 5218, "time": 2153}, {"level": 13, "ability": 5218, "time": 2236}, {"level": 14, "ability": 5218, "time": 2549}, {"level": 15, "ability": 5002, "time": 2898}, {"level": 16, "ability": 5221, "time": 3123}, {"level": 17, "ability": 5002, "time": 3458}, {"level": 18, "ability": 5002, "time": 3701}, {"level": 19, "ability": 5002, "time": 3764}], "assists": 10, "hero_damage": 11011, "denies": 12, "gold": 1930, "hero_healing": 1212, "level": 19, "leaver_status": 0, "gold_spent": 16070, "item_1": 63, "item_0": 0, "item_2": 90, "player_slot": 2, "gold_per_min": 392, "item_3": 79, "xp_per_min": 396, "hero_id": 47, "item_4": 108}, {"tower_damage": 279, "item_5": 31, "deaths": 5, "kills": 3, "last_hits": 168, "account_id": 106443009, "ability_upgrades": [{"level": 1, "ability": 5120, "time": 849}, {"level": 2, "ability": 5119, "time": 902}, {"level": 3, "ability": 5120, "time": 937}, {"level": 4, "ability": 5119, "time": 1005}, {"level": 5, "ability": 5120, "time": 1071}, {"level": 6, "ability": 5121, "time": 1157}, {"level": 7, "ability": 5118, "time": 1256}, {"level": 8, "ability": 5120, "time": 1293}, {"level": 9, "ability": 5119, "time": 1560}, {"level": 10, "ability": 5119, "time": 1641}, {"level": 11, "ability": 5121, "time": 1737}, {"level": 12, "ability": 5118, "time": 1909}, {"level": 13, "ability": 5118, "time": 2146}, {"level": 14, "ability": 5118, "time": 2259}, {"level": 15, "ability": 5002, "time": 2483}, {"level": 16, "ability": 5121, "time": 2873}, {"level": 17, "ability": 5002, "time": 3089}, {"level": 18, "ability": 5002, "time": 3501}, {"level": 19, "ability": 5002, "time": 3726}, {"level": 20, "ability": 5002, "time": 3759}], "assists": 18, "hero_damage": 11762, "denies": 4, "gold": 3318, "hero_healing": 0, "level": 20, "leaver_status": 0, "gold_spent": 15800, "item_1": 119, "item_0": 1, "item_2": 30, "player_slot": 3, "gold_per_min": 400, "item_3": 180, "xp_per_min": 445, "hero_id": 29, "item_4": 110}, {"tower_damage": 3552, "item_5": 114, "deaths": 3, "kills": 8, "last_hits": 624, "account_id": 91191397, "ability_upgrades": [{"level": 1, "ability": 5469, "time": 840}, {"level": 2, "ability": 5468, "time": 913}, {"level": 3, "ability": 5469, "time": 980}, {"level": 4, "ability": 5468, "time": 1109}, {"level": 5, "ability": 5469, "time": 1212}, {"level": 6, "ability": 5470, "time": 1285}, {"level": 7, "ability": 5469, "time": 1385}, {"level": 8, "ability": 5467, "time": 1454}, {"level": 9, "ability": 5467, "time": 1656}, {"level": 10, "ability": 5467, "time": 1789}, {"level": 11, "ability": 5467, "time": 1901}, {"level": 12, "ability": 5470, "time": 1927}, {"level": 13, "ability": 5468, "time": 1993}, {"level": 14, "ability": 5468, "time": 2155}, {"level": 15, "ability": 5002, "time": 2379}, {"level": 16, "ability": 5470, "time": 2532}, {"level": 17, "ability": 5002, "time": 2717}, {"level": 18, "ability": 5002, "time": 2964}, {"level": 19, "ability": 5002, "time": 2964}, {"level": 20, "ability": 5002, "time": 3078}, {"level": 21, "ability": 5002, "time": 3264}, {"level": 22, "ability": 5002, "time": 3429}, {"level": 23, "ability": 5002, "time": 3594}, {"level": 24, "ability": 5002, "time": 3767}, {"level": 25, "ability": 5002, "time": 3767}], "assists": 14, "hero_damage": 19385, "denies": 9, "gold": 5966, "hero_healing": 0, "level": 25, "leaver_status": 0, "gold_spent": 32705, "item_1": 139, "item_0": 147, "item_2": 123, "player_slot": 4, "gold_per_min": 781, "item_3": 137, "xp_per_min": 659, "hero_id": 89, "item_4": 48}, {"tower_damage": 1720, "item_5": 156, "deaths": 9, "kills": 3, "last_hits": 520, "account_id": 95566398, "ability_upgrades": [{"level": 1, "ability": 5224, "time": 766}, {"level": 2, "ability": 5222, "time": 940}, {"level": 3, "ability": 5222, "time": 1012}, {"level": 4, "ability": 5224, "time": 1185}, {"level": 5, "ability": 5222, "time": 1251}, {"level": 6, "ability": 5225, "time": 1389}, {"level": 7, "ability": 5222, "time": 1474}, {"level": 8, "ability": 5224, "time": 1539}, {"level": 9, "ability": 5224, "time": 1710}, {"level": 10, "ability": 5223, "time": 1816}, {"level": 11, "ability": 5225, "time": 1880}, {"level": 12, "ability": 5223, "time": 2200}, {"level": 13, "ability": 5223, "time": 2265}, {"level": 14, "ability": 5223, "time": 2376}, {"level": 15, "ability": 5002, "time": 2544}, {"level": 16, "ability": 5225, "time": 2591}, {"level": 17, "ability": 5002, "time": 2700}, {"level": 18, "ability": 5002, "time": 2813}, {"level": 19, "ability": 5002, "time": 2954}, {"level": 20, "ability": 5002, "time": 3123}, {"level": 21, "ability": 5002, "time": 3295}, {"level": 22, "ability": 5002, "time": 3417}, {"level": 23, "ability": 5002, "time": 3562}], "assists": 7, "hero_damage": 8956, "denies": 16, "gold": 0, "hero_healing": 0, "level": 23, "leaver_status": 0, "gold_spent": 27770, "item_1": 147, "item_0": 63, "item_2": 139, "player_slot": 128, "gold_per_min": 637, "item_3": 116, "xp_per_min": 596, "hero_id": 48, "item_4": 0}, {"tower_damage": 91, "item_5": 0, "deaths": 6, "kills": 3, "last_hits": 77, "account_id": 96307331, "ability_upgrades": [{"level": 1, "ability": 5330, "time": 787}, {"level": 2, "ability": 5329, "time": 916}, {"level": 3, "ability": 5329, "time": 1035}, {"level": 4, "ability": 5330, "time": 1200}, {"level": 5, "ability": 5330, "time": 1485}, {"level": 6, "ability": 5331, "time": 1692}, {"level": 7, "ability": 5330, "time": 1759}, {"level": 8, "ability": 5329, "time": 1788}, {"level": 9, "ability": 5329, "time": 2078}, {"level": 10, "ability": 5328, "time": 2497}, {"level": 11, "ability": 5331, "time": 2579}, {"level": 12, "ability": 5328, "time": 2919}, {"level": 13, "ability": 5328, "time": 2981}, {"level": 14, "ability": 5328, "time": 3450}], "assists": 8, "hero_damage": 3664, "denies": 0, "gold": 1122, "hero_healing": 2807, "level": 14, "leaver_status": 0, "gold_spent": 8690, "item_1": 0, "item_0": 79, "item_2": 46, "player_slot": 129, "gold_per_min": 211, "item_3": 102, "xp_per_min": 226, "hero_id": 66, "item_4": 29}, {"tower_damage": 268, "item_5": 0, "deaths": 4, "kills": 6, "last_hits": 107, "account_id": 86772934, "ability_upgrades": [{"level": 1, "ability": 5320, "time": 786}, {"level": 2, "ability": 5322, "time": 890}, {"level": 3, "ability": 5320, "time": 953}, {"level": 4, "ability": 5322, "time": 1042}, {"level": 5, "ability": 5320, "time": 1107}, {"level": 6, "ability": 5323, "time": 1194}, {"level": 7, "ability": 5320, "time": 1288}, {"level": 8, "ability": 5322, "time": 1352}, {"level": 9, "ability": 5321, "time": 1483}, {"level": 10, "ability": 5321, "time": 1669}, {"level": 11, "ability": 5323, "time": 1692}, {"level": 12, "ability": 5321, "time": 2002}, {"level": 13, "ability": 5321, "time": 2377}, {"level": 14, "ability": 5322, "time": 2578}, {"level": 15, "ability": 5002, "time": 2898}, {"level": 16, "ability": 5323, "time": 2954}, {"level": 17, "ability": 5002, "time": 3150}, {"level": 18, "ability": 5002, "time": 3593}], "assists": 11, "hero_damage": 8490, "denies": 8, "gold": 2432, "hero_healing": 0, "level": 18, "leaver_status": 0, "gold_spent": 10670, "item_1": 102, "item_0": 214, "item_2": 1, "player_slot": 130, "gold_per_min": 282, "item_3": 46, "xp_per_min": 361, "hero_id": 65, "item_4": 116}, {"tower_damage": 99, "item_5": 188, "deaths": 6, "kills": 2, "last_hits": 23, "account_id": 102096245, "ability_upgrades": [{"level": 1, "ability": 5122, "time": 767}, {"level": 2, "ability": 5123, "time": 969}, {"level": 3, "ability": 5124, "time": 1090}, {"level": 4, "ability": 5122, "time": 1246}, {"level": 5, "ability": 5123, "time": 1328}, {"level": 6, "ability": 5125, "time": 1494}, {"level": 7, "ability": 5123, "time": 1687}, {"level": 8, "ability": 5123, "time": 1728}, {"level": 9, "ability": 5122, "time": 1901}, {"level": 10, "ability": 5125, "time": 1925}, {"level": 11, "ability": 5124, "time": 1940}, {"level": 12, "ability": 5124, "time": 2584}, {"level": 13, "ability": 5124, "time": 2689}, {"level": 14, "ability": 5122, "time": 3146}, {"level": 15, "ability": 5002, "time": 3569}], "assists": 14, "hero_damage": 4688, "denies": 4, "gold": 827, "hero_healing": 151, "level": 15, "leaver_status": 0, "gold_spent": 5940, "item_1": 36, "item_0": 92, "item_2": 214, "player_slot": 131, "gold_per_min": 179, "item_3": 73, "xp_per_min": 259, "hero_id": 20, "item_4": 42}, {"tower_damage": 0, "item_5": 9, "deaths": 2, "kills": 6, "last_hits": 105, "account_id": 152800969, "ability_upgrades": [{"level": 1, "ability": 5102, "time": 889}, {"level": 2, "ability": 5103, "time": 890}, {"level": 3, "ability": 5102, "time": 927}, {"level": 4, "ability": 5103, "time": 988}, {"level": 5, "ability": 5102, "time": 1076}, {"level": 6, "ability": 5105, "time": 1158}, {"level": 7, "ability": 5102, "time": 1301}, {"level": 8, "ability": 5103, "time": 1470}, {"level": 9, "ability": 5103, "time": 1528}, {"level": 10, "ability": 5104, "time": 1669}, {"level": 11, "ability": 5105, "time": 1692}, {"level": 12, "ability": 5104, "time": 1923}, {"level": 13, "ability": 5104, "time": 2075}, {"level": 14, "ability": 5002, "time": 2353}, {"level": 15, "ability": 5002, "time": 2764}, {"level": 16, "ability": 5105, "time": 2905}, {"level": 17, "ability": 5104, "time": 3516}, {"level": 18, "ability": 5002, "time": 3701}], "assists": 13, "hero_damage": 11912, "denies": 3, "gold": 1678, "hero_healing": 0, "level": 18, "leaver_status": 0, "gold_spent": 12435, "item_1": 36, "item_0": 190, "item_2": 180, "player_slot": 132, "gold_per_min": 279, "item_3": 1, "xp_per_min": 349, "hero_id": 16, "item_4": 102}], "radiant_team_id": 24, "lobby_type": 1, "match_id": 666517998, "leagueid": 600, "radiant_team_complete": 1, "radiant_logo": 884111088312994582, "duration": 2971, "negative_votes": 847, "radiant_win": true, "picks_bans": [{"is_pick": false, "team": 1, "hero_id": 106, "order": 0}, {"is_pick": false, "team": 0, "hero_id": 74, "order": 1}, {"is_pick": false, "team": 1, "hero_id": 69, "order": 2}, {"is_pick": false, "team": 0, "hero_id": 77, "order": 3}, {"is_pick": true, "team": 1, "hero_id": 65, "order": 4}, {"is_pick": true, "team": 0, "hero_id": 89, "order": 5}, {"is_pick": true, "team": 0, "hero_id": 83, "order": 6}, {"is_pick": true, "team": 1, "hero_id": 16, "order": 7}, {"is_pick": false, "team": 1, "hero_id": 79, "order": 8}, {"is_pick": false, "team": 0, "hero_id": 10, "order": 9}, {"is_pick": false, "team": 1, "hero_id": 86, "order": 10}, {"is_pick": false, "team": 0, "hero_id": 63, "order": 11}, {"is_pick": true, "team": 0, "hero_id": 47, "order": 12}, {"is_pick": true, "team": 1, "hero_id": 66, "order": 13}, {"is_pick": true, "team": 0, "hero_id": 29, "order": 14}, {"is_pick": true, "team": 1, "hero_id": 20, "order": 15}, {"is_pick": false, "team": 0, "hero_id": 1, "order": 16}, {"is_pick": false, "team": 1, "hero_id": 68, "order": 17}, {"is_pick": true, "team": 0, "hero_id": 64, "order": 18}, {"is_pick": true, "team": 1, "hero_id": 48, "order": 19}], "dire_logo": 612792385922460575, "dire_team_id": 543897, "dire_team_complete": 1, "match_seq_num": 603303990, "game_mode": 2, "barracks_status_dire": 63, "radiant_name": "MiTH-Trust", "human_players": 10, "cluster": 151, "positive_votes": 7086, "tower_status_radiant": 1974}}